opendrive2lanelet/__init__.py
opendrive2lanelet/conversion_lanelet.py
opendrive2lanelet/conversion_lanelet_network.py
opendrive2lanelet/converter.py
opendrive2lanelet/network.py
opendrive2lanelet/utils.py
opendrive2lanelet/io/__init__.py
opendrive2lanelet/io/gui.py
opendrive2lanelet/io/opendrive_convert.py
opendrive2lanelet/io/osm_convert.py
opendrive2lanelet/io/viewer.py
opendrive2lanelet/io/visualize_commonroad.py
opendrive2lanelet/opendriveparser/__init__.py
opendrive2lanelet/opendriveparser/parser.py
opendrive2lanelet/opendriveparser/elements/__init__.py
opendrive2lanelet/opendriveparser/elements/eulerspiral.py
opendrive2lanelet/opendriveparser/elements/geometry.py
opendrive2lanelet/opendriveparser/elements/junction.py
opendrive2lanelet/opendriveparser/elements/opendrive.py
opendrive2lanelet/opendriveparser/elements/road.py
opendrive2lanelet/opendriveparser/elements/roadElevationProfile.py
opendrive2lanelet/opendriveparser/elements/roadLanes.py
opendrive2lanelet/opendriveparser/elements/roadLateralProfile.py
opendrive2lanelet/opendriveparser/elements/roadLink.py
opendrive2lanelet/opendriveparser/elements/roadPlanView.py
opendrive2lanelet/opendriveparser/elements/road_record.py
opendrive2lanelet/opendriveparser/elements/roadtype.py
opendrive2lanelet/osm/__init__.py
opendrive2lanelet/osm/lanelet2osm.py
opendrive2lanelet/osm/osm.py
opendrive2lanelet/osm/osm2lanelet.py
opendrive2lanelet/osm/parser.py
opendrive2lanelet/plane_elements/__init__.py
opendrive2lanelet/plane_elements/border.py
opendrive2lanelet/plane_elements/plane.py
opendrive2lanelet/plane_elements/plane_group.py
opendrive2lanelet-1.2.1.dist-info/LICENSE.txt
opendrive2lanelet-1.2.1.dist-info/METADATA
opendrive2lanelet-1.2.1.dist-info/WHEEL
opendrive2lanelet-1.2.1.dist-info/entry_points.txt
opendrive2lanelet-1.2.1.dist-info/top_level.txt
opendrive2lanelet-1.2.1.dist-info/RECORD
