Metadata-Version: 2.1
Name: opendrive2lanelet
Version: 1.2.1
Summary: Parser and converter from OpenDRIVE to lanelets
Home-page: https://commonroad.in.tum.de/
Author: Technical University of Munich
Author-email: commonroad@lists.lrz.de
License: GNU General Public License v3.0
Platform: UNKNOWN
Classifier: Development Status :: 5 - Production/Stable
Classifier: License :: OSI Approved :: GNU General Public License v3 (GPLv3)
Classifier: Programming Language :: Python :: 3.6
Classifier: Programming Language :: Python :: 3.7
Classifier: Operating System :: MacOS
Classifier: Operating System :: Microsoft :: Windows
Classifier: Operating System :: POSIX
Classifier: Operating System :: Unix
Requires-Python: >=3.6
Requires-Dist: numpy (>=1.16.4)
Requires-Dist: lxml (>=4.3.4)
Requires-Dist: commonroad-io (>=2020.2)
Requires-Dist: pyproj (>=2.2.0)
Requires-Dist: scipy (>=1.3.0)
Provides-Extra: gui
Requires-Dist: PyQt5 (>=5.12.2) ; extra == 'gui'
Requires-Dist: matplotlib (>=3.1.0) ; extra == 'gui'
